arab_transliterator/__init__.py
arab_transliterator/alphabet.py
arab_transliterator/arab_text.py
arab_transliterator/mapping.py
arab_transliterator/transliterator.py
arab_transliterator/_types/__init__.py
arab_transliterator/_types/linked_queue.py
arab_transliterator-1.0.3.dist-info/METADATA
arab_transliterator-1.0.3.dist-info/WHEEL
arab_transliterator-1.0.3.dist-info/top_level.txt
arab_transliterator-1.0.3.dist-info/RECORD
