Metadata-Version: 2.1
Name: arab-transliterator
Version: 1.0.3
Summary: python script for arabic text transcription
Home-page: https://github.com/Tariha/transcription
Author: Linzo99
Author-email: Linzo99 <sallalioune99@gmail.com>
Project-URL: Homepage, https://github.com/Tariha/transcription
Requires-Python: >=3.9
